pyhabr_proxy/__init__.py
pyhabr_proxy/_getsense_main.py
pyhabr_proxy/_getsense_proxy.py
pyhabr_proxy-0.1.dist-info/METADATA
pyhabr_proxy-0.1.dist-info/WHEEL
pyhabr_proxy-0.1.dist-info/top_level.txt
pyhabr_proxy-0.1.dist-info/RECORD
