Metadata-Version: 2.1
Name: pyhabr-proxy
Version: 0.1
Summary: local habr.com proxy
Home-page: UNKNOWN
Author: Nikita Kuzin
Author-email: getsense@yandex.ru
License: UNKNOWN
Platform: UNKNOWN
Classifier: Programming Language :: Python :: 3
Classifier: License :: Freeware
Classifier: Operating System :: OS Independent
